MANIFEST.in
setup.py
coreapi/__init__.py
coreapi/client.py
coreapi/compat.py
coreapi/document.py
coreapi/exceptions.py
coreapi/utils.py
coreapi/codecs/__init__.py
coreapi/codecs/base.py
coreapi/codecs/corejson.py
coreapi/codecs/display.py
coreapi/codecs/download.py
coreapi/codecs/jsondata.py
coreapi/codecs/python.py
coreapi/codecs/text.py
coreapi/transports/__init__.py
coreapi/transports/base.py
coreapi/transports/http.py
coreapi_devin.egg-info/PKG-INFO
coreapi_devin.egg-info/SOURCES.txt
coreapi_devin.egg-info/dependency_links.txt
coreapi_devin.egg-info/entry_points.txt
coreapi_devin.egg-info/requires.txt
coreapi_devin.egg-info/top_level.txt