Metadata-Version: 1.1
Name: coreapi-devin
Version: 2.0.7
Summary: Python client library for Core API.
Home-page: https://github.com/waipbmtd/python-client
Author: Devin
Author-email: waipbmtd@gmail.com
License: BSD
Platform: UNKNOWN
Classifier: Development Status :: 3 - Alpha
Classifier: Environment :: Web Environment
Classifier: Intended Audience :: Developers
Classifier: License :: OSI Approved :: BSD License
Classifier: Operating System :: OS Independent
Classifier: Programming Language :: Python
Classifier: Topic :: Internet :: WWW/HTTP
